aadc/__init__.py
aadc/_aadc_core.cp39-win_amd64.pyd
aadc/_aadc_core.pyi
aadc/evaluate_wrappers.py
aadc/ndarray.py
aadc/overrides.py
aadc/overrides_free.py
aadc/py.typed
aadc/quantlib.py
aadc/record_function.py
aadc/recording_ctx.py
aadc/utils.py
aadc/vectorize.py
aadc/numpy_compat/function_bindings.py
aadc/numpy_compat/mainpulation_functions.py
aadc/numpy_compat/other_functions.py
aadc/numpy_compat/scalar_numpy_compat.py
aadc/numpy_compat/statistical_functions.py
aadc/numpy_compat/ufuncs.py
aadc/scipy/interpolate.py
aadc-1.8.0.dist-info/licenses/LICENSE.txt
aadc-1.8.0.dist-info/METADATA
aadc-1.8.0.dist-info/WHEEL
aadc-1.8.0.dist-info/top_level.txt
aadc-1.8.0.dist-info/RECORD
