Metadata-Version: 2.4
Name: aadc
Version: 1.8.0
Summary: Python interface to AADC
Author: Matlogica
Author-email: info@matlogica.com
Requires-Python: >=3.8
License-File: LICENSE.txt
Requires-Dist: numpy>=1.21.0
Requires-Dist: scipy<=1.14.1
Provides-Extra: test
Requires-Dist: pytest; extra == "test"
Dynamic: author
Dynamic: author-email
Dynamic: license-file
Dynamic: provides-extra
Dynamic: requires-dist
Dynamic: requires-python
Dynamic: summary
